README.txt
setup.py
puploadr/__init__.py
puploadr/puploadr.py
puploadr.egg-info/PKG-INFO
puploadr.egg-info/SOURCES.txt
puploadr.egg-info/dependency_links.txt
puploadr.egg-info/entry_points.txt
puploadr.egg-info/requires.txt
puploadr.egg-info/top_level.txt