Metadata-Version: 1.0
Name: puploadr
Version: 0.2
Summary: Yet another flickr uploader script with resume capabilities
Home-page: UNKNOWN
Author: Elek, Marton
Author-email: UNKNOWN
License: GPL
Platform: UNKNOWN
